{"_path":"/leetcode/undirected-path","_dir":"leetcode","_draft":false,"_partial":false,"_locale":"","_empty":false,"title":"Undirected Path","description":"My Solution:","problemUrl":"https://structy.net/problems/undirected-path","tags":["python","graph","traversal"],"body":{"type":"root","children":[{"type":"element","tag":"p","props":{},"children":[{"type":"element","tag":"strong","props":{},"children":[{"type":"text","value":"My Solution"}]},{"type":"text","value":":"}]},{"type":"element","tag":"code","props":{"className":["language-py"],"code":"def undirected_path(edges, node_A, node_B):\n    adj_list = {}\n\n    # Convert edge list into adjacency list\n    for e in edges:   \n        if e[0] not in adj_list:\n            adj_list[e[0]] = []\n        if e[1] not in adj_list:\n            adj_list[e[1]] = []\n\n        adj_list[e[1]].append(e[0])\n        adj_list[e[0]].append(e[1])\n\n    stack = [node_A]\n    visited = []\n\n    # Traverse the undirected graph\n    while len(stack) > 0:\n        current = stack.pop(0)\n\n        if current == node_B:\n            return True\n\n        if current in visited:\n            continue\n\n        visited.append(current)\n\n        for e in adj_list[current]:\n            stack.append(e)\n\n    return False\n","language":"py","meta":""},"children":[{"type":"element","tag":"pre","props":{},"children":[{"type":"element","tag":"code","props":{"__ignoreMap":""},"children":[{"type":"element","tag":"span","props":{"class":"line","line":1},"children":[{"type":"element","tag":"span","props":{"class":"ct-422695"},"children":[{"type":"text","value":"def"}]},{"type":"element","tag":"span","props":{"class":"ct-212021"},"children":[{"type":"text","value":" "}]},{"type":"element","tag":"span","props":{"class":"ct-215352"},"children":[{"type":"text","value":"undirected_path"}]},{"type":"element","tag":"span","props":{"class":"ct-212021"},"children":[{"type":"text","value":"(edges, node_A, node_B):\n"}]}]},{"type":"element","tag":"span","props":{"class":"line","line":2},"children":[{"type":"element","tag":"span","props":{"class":"ct-212021"},"children":[{"type":"text","value":"    adj_list "}]},{"type":"element","tag":"span","props":{"class":"ct-422695"},"children":[{"type":"text","value":"="}]},{"type":"element","tag":"span","props":{"class":"ct-212021"},"children":[{"type":"text","value":" {}\n"}]}]},{"type":"element","tag":"span","props":{"class":"line","line":3},"children":[{"type":"element","tag":"span","props":{},"children":[{"type":"text","value":"\n"}]}]},{"type":"element","tag":"span","props":{"class":"line","line":4},"children":[{"type":"element","tag":"span","props":{"class":"ct-212021"},"children":[{"type":"text","value":"    "}]},{"type":"element","tag":"span","props":{"class":"ct-188924"},"children":[{"type":"text","value":"# Convert edge list into adjacency list\n"}]}]},{"type":"element","tag":"span","props":{"class":"line","line":5},"children":[{"type":"element","tag":"span","props":{"class":"ct-212021"},"children":[{"type":"text","value":"    "}]},{"type":"element","tag":"span","props":{"class":"ct-422695"},"children":[{"type":"text","value":"for"}]},{"type":"element","tag":"span","props":{"class":"ct-212021"},"children":[{"type":"text","value":" e "}]},{"type":"element","tag":"span","props":{"class":"ct-422695"},"children":[{"type":"text","value":"in"}]},{"type":"element","tag":"span","props":{"class":"ct-212021"},"children":[{"type":"text","value":" edges:   \n"}]}]},{"type":"element","tag":"span","props":{"class":"line","line":6},"children":[{"type":"element","tag":"span","props":{"class":"ct-212021"},"children":[{"type":"text","value":"        "}]},{"type":"element","tag":"span","props":{"class":"ct-422695"},"children":[{"type":"text","value":"if"}]},{"type":"element","tag":"span","props":{"class":"ct-212021"},"children":[{"type":"text","value":" e["}]},{"type":"element","tag":"span","props":{"class":"ct-848546"},"children":[{"type":"text","value":"0"}]},{"type":"element","tag":"span","props":{"class":"ct-212021"},"children":[{"type":"text","value":"] "}]},{"type":"element","tag":"span","props":{"class":"ct-422695"},"children":[{"type":"text","value":"not"}]},{"type":"element","tag":"span","props":{"class":"ct-212021"},"children":[{"type":"text","value":" "}]},{"type":"element","tag":"span","props":{"class":"ct-422695"},"children":[{"type":"text","value":"in"}]},{"type":"element","tag":"span","props":{"class":"ct-212021"},"children":[{"type":"text","value":" adj_list:\n"}]}]},{"type":"element","tag":"span","props":{"class":"line","line":7},"children":[{"type":"element","tag":"span","props":{"class":"ct-212021"},"children":[{"type":"text","value":"            adj_list[e["}]},{"type":"element","tag":"span","props":{"class":"ct-848546"},"children":[{"type":"text","value":"0"}]},{"type":"element","tag":"span","props":{"class":"ct-212021"},"children":[{"type":"text","value":"]] "}]},{"type":"element","tag":"span","props":{"class":"ct-422695"},"children":[{"type":"text","value":"="}]},{"type":"element","tag":"span","props":{"class":"ct-212021"},"children":[{"type":"text","value":" []\n"}]}]},{"type":"element","tag":"span","props":{"class":"line","line":8},"children":[{"type":"element","tag":"span","props":{"class":"ct-212021"},"children":[{"type":"text","value":"        "}]},{"type":"element","tag":"span","props":{"class":"ct-422695"},"children":[{"type":"text","value":"if"}]},{"type":"element","tag":"span","props":{"class":"ct-212021"},"children":[{"type":"text","value":" e["}]},{"type":"element","tag":"span","props":{"class":"ct-848546"},"children":[{"type":"text","value":"1"}]},{"type":"element","tag":"span","props":{"class":"ct-212021"},"children":[{"type":"text","value":"] "}]},{"type":"element","tag":"span","props":{"class":"ct-422695"},"children":[{"type":"text","value":"not"}]},{"type":"element","tag":"span","props":{"class":"ct-212021"},"children":[{"type":"text","value":" "}]},{"type":"element","tag":"span","props":{"class":"ct-422695"},"children":[{"type":"text","value":"in"}]},{"type":"element","tag":"span","props":{"class":"ct-212021"},"children":[{"type":"text","value":" adj_list:\n"}]}]},{"type":"element","tag":"span","props":{"class":"line","line":9},"children":[{"type":"element","tag":"span","props":{"class":"ct-212021"},"children":[{"type":"text","value":"            adj_list[e["}]},{"type":"element","tag":"span","props":{"class":"ct-848546"},"children":[{"type":"text","value":"1"}]},{"type":"element","tag":"span","props":{"class":"ct-212021"},"children":[{"type":"text","value":"]] "}]},{"type":"element","tag":"span","props":{"class":"ct-422695"},"children":[{"type":"text","value":"="}]},{"type":"element","tag":"span","props":{"class":"ct-212021"},"children":[{"type":"text","value":" []\n"}]}]},{"type":"element","tag":"span","props":{"class":"line","line":10},"children":[{"type":"element","tag":"span","props":{},"children":[{"type":"text","value":"\n"}]}]},{"type":"element","tag":"span","props":{"class":"line","line":11},"children":[{"type":"element","tag":"span","props":{"class":"ct-212021"},"children":[{"type":"text","value":"        adj_list[e["}]},{"type":"element","tag":"span","props":{"class":"ct-848546"},"children":[{"type":"text","value":"1"}]},{"type":"element","tag":"span","props":{"class":"ct-212021"},"children":[{"type":"text","value":"]].append(e["}]},{"type":"element","tag":"span","props":{"class":"ct-848546"},"children":[{"type":"text","value":"0"}]},{"type":"element","tag":"span","props":{"class":"ct-212021"},"children":[{"type":"text","value":"])\n"}]}]},{"type":"element","tag":"span","props":{"class":"line","line":12},"children":[{"type":"element","tag":"span","props":{"class":"ct-212021"},"children":[{"type":"text","value":"        adj_list[e["}]},{"type":"element","tag":"span","props":{"class":"ct-848546"},"children":[{"type":"text","value":"0"}]},{"type":"element","tag":"span","props":{"class":"ct-212021"},"children":[{"type":"text","value":"]].append(e["}]},{"type":"element","tag":"span","props":{"class":"ct-848546"},"children":[{"type":"text","value":"1"}]},{"type":"element","tag":"span","props":{"class":"ct-212021"},"children":[{"type":"text","value":"])\n"}]}]},{"type":"element","tag":"span","props":{"class":"line","line":13},"children":[{"type":"element","tag":"span","props":{},"children":[{"type":"text","value":"\n"}]}]},{"type":"element","tag":"span","props":{"class":"line","line":14},"children":[{"type":"element","tag":"span","props":{"class":"ct-212021"},"children":[{"type":"text","value":"    stack "}]},{"type":"element","tag":"span","props":{"class":"ct-422695"},"children":[{"type":"text","value":"="}]},{"type":"element","tag":"span","props":{"class":"ct-212021"},"children":[{"type":"text","value":" [node_A]\n"}]}]},{"type":"element","tag":"span","props":{"class":"line","line":15},"children":[{"type":"element","tag":"span","props":{"class":"ct-212021"},"children":[{"type":"text","value":"    visited "}]},{"type":"element","tag":"span","props":{"class":"ct-422695"},"children":[{"type":"text","value":"="}]},{"type":"element","tag":"span","props":{"class":"ct-212021"},"children":[{"type":"text","value":" []\n"}]}]},{"type":"element","tag":"span","props":{"class":"line","line":16},"children":[{"type":"element","tag":"span","props":{},"children":[{"type":"text","value":"\n"}]}]},{"type":"element","tag":"span","props":{"class":"line","line":17},"children":[{"type":"element","tag":"span","props":{"class":"ct-212021"},"children":[{"type":"text","value":"    "}]},{"type":"element","tag":"span","props":{"class":"ct-188924"},"children":[{"type":"text","value":"# Traverse the undirected graph\n"}]}]},{"type":"element","tag":"span","props":{"class":"line","line":18},"children":[{"type":"element","tag":"span","props":{"class":"ct-212021"},"children":[{"type":"text","value":"    "}]},{"type":"element","tag":"span","props":{"class":"ct-422695"},"children":[{"type":"text","value":"while"}]},{"type":"element","tag":"span","props":{"class":"ct-212021"},"children":[{"type":"text","value":" "}]},{"type":"element","tag":"span","props":{"class":"ct-848546"},"children":[{"type":"text","value":"len"}]},{"type":"element","tag":"span","props":{"class":"ct-212021"},"children":[{"type":"text","value":"(stack) "}]},{"type":"element","tag":"span","props":{"class":"ct-422695"},"children":[{"type":"text","value":">"}]},{"type":"element","tag":"span","props":{"class":"ct-212021"},"children":[{"type":"text","value":" "}]},{"type":"element","tag":"span","props":{"class":"ct-848546"},"children":[{"type":"text","value":"0"}]},{"type":"element","tag":"span","props":{"class":"ct-212021"},"children":[{"type":"text","value":":\n"}]}]},{"type":"element","tag":"span","props":{"class":"line","line":19},"children":[{"type":"element","tag":"span","props":{"class":"ct-212021"},"children":[{"type":"text","value":"        current "}]},{"type":"element","tag":"span","props":{"class":"ct-422695"},"children":[{"type":"text","value":"="}]},{"type":"element","tag":"span","props":{"class":"ct-212021"},"children":[{"type":"text","value":" stack.pop("}]},{"type":"element","tag":"span","props":{"class":"ct-848546"},"children":[{"type":"text","value":"0"}]},{"type":"element","tag":"span","props":{"class":"ct-212021"},"children":[{"type":"text","value":")\n"}]}]},{"type":"element","tag":"span","props":{"class":"line","line":20},"children":[{"type":"element","tag":"span","props":{},"children":[{"type":"text","value":"\n"}]}]},{"type":"element","tag":"span","props":{"class":"line","line":21},"children":[{"type":"element","tag":"span","props":{"class":"ct-212021"},"children":[{"type":"text","value":"        "}]},{"type":"element","tag":"span","props":{"class":"ct-422695"},"children":[{"type":"text","value":"if"}]},{"type":"element","tag":"span","props":{"class":"ct-212021"},"children":[{"type":"text","value":" current "}]},{"type":"element","tag":"span","props":{"class":"ct-422695"},"children":[{"type":"text","value":"=="}]},{"type":"element","tag":"span","props":{"class":"ct-212021"},"children":[{"type":"text","value":" node_B:\n"}]}]},{"type":"element","tag":"span","props":{"class":"line","line":22},"children":[{"type":"element","tag":"span","props":{"class":"ct-212021"},"children":[{"type":"text","value":"            "}]},{"type":"element","tag":"span","props":{"class":"ct-422695"},"children":[{"type":"text","value":"return"}]},{"type":"element","tag":"span","props":{"class":"ct-212021"},"children":[{"type":"text","value":" "}]},{"type":"element","tag":"span","props":{"class":"ct-848546"},"children":[{"type":"text","value":"True\n"}]}]},{"type":"element","tag":"span","props":{"class":"line","line":23},"children":[{"type":"element","tag":"span","props":{},"children":[{"type":"text","value":"\n"}]}]},{"type":"element","tag":"span","props":{"class":"line","line":24},"children":[{"type":"element","tag":"span","props":{"class":"ct-212021"},"children":[{"type":"text","value":"        "}]},{"type":"element","tag":"span","props":{"class":"ct-422695"},"children":[{"type":"text","value":"if"}]},{"type":"element","tag":"span","props":{"class":"ct-212021"},"children":[{"type":"text","value":" current "}]},{"type":"element","tag":"span","props":{"class":"ct-422695"},"children":[{"type":"text","value":"in"}]},{"type":"element","tag":"span","props":{"class":"ct-212021"},"children":[{"type":"text","value":" visited:\n"}]}]},{"type":"element","tag":"span","props":{"class":"line","line":25},"children":[{"type":"element","tag":"span","props":{"class":"ct-212021"},"children":[{"type":"text","value":"            "}]},{"type":"element","tag":"span","props":{"class":"ct-422695"},"children":[{"type":"text","value":"continue\n"}]}]},{"type":"element","tag":"span","props":{"class":"line","line":26},"children":[{"type":"element","tag":"span","props":{},"children":[{"type":"text","value":"\n"}]}]},{"type":"element","tag":"span","props":{"class":"line","line":27},"children":[{"type":"element","tag":"span","props":{"class":"ct-212021"},"children":[{"type":"text","value":"        visited.append(current)\n"}]}]},{"type":"element","tag":"span","props":{"class":"line","line":28},"children":[{"type":"element","tag":"span","props":{},"children":[{"type":"text","value":"\n"}]}]},{"type":"element","tag":"span","props":{"class":"line","line":29},"children":[{"type":"element","tag":"span","props":{"class":"ct-212021"},"children":[{"type":"text","value":"        "}]},{"type":"element","tag":"span","props":{"class":"ct-422695"},"children":[{"type":"text","value":"for"}]},{"type":"element","tag":"span","props":{"class":"ct-212021"},"children":[{"type":"text","value":" e "}]},{"type":"element","tag":"span","props":{"class":"ct-422695"},"children":[{"type":"text","value":"in"}]},{"type":"element","tag":"span","props":{"class":"ct-212021"},"children":[{"type":"text","value":" adj_list[current]:\n"}]}]},{"type":"element","tag":"span","props":{"class":"line","line":30},"children":[{"type":"element","tag":"span","props":{"class":"ct-212021"},"children":[{"type":"text","value":"            stack.append(e)\n"}]}]},{"type":"element","tag":"span","props":{"class":"line","line":31},"children":[{"type":"element","tag":"span","props":{},"children":[{"type":"text","value":"\n"}]}]},{"type":"element","tag":"span","props":{"class":"line","line":32},"children":[{"type":"element","tag":"span","props":{"class":"ct-212021"},"children":[{"type":"text","value":"    "}]},{"type":"element","tag":"span","props":{"class":"ct-422695"},"children":[{"type":"text","value":"return"}]},{"type":"element","tag":"span","props":{"class":"ct-212021"},"children":[{"type":"text","value":" "}]},{"type":"element","tag":"span","props":{"class":"ct-848546"},"children":[{"type":"text","value":"False"}]}]}]}]}]},{"type":"element","tag":"style","children":[{"type":"text","value":".ct-422695{color:#FF7B72;}\n.ct-212021{color:#C9D1D9;}\n.ct-215352{color:#D2A8FF;}\n.ct-188924{color:#8B949E;}\n.ct-848546{color:#79C0FF;}"}]}],"toc":{"title":"","searchDepth":2,"depth":1,"links":[]}},"_type":"markdown","_id":"content:leetcode:undirected-path.md","_source":"content","_file":"leetcode/undirected-path.md","_extension":"md"}